[
  {
    "Name": "Ku Tak Bisa",
    "Artist": "Slank",
    "Link": "https://www.youtube.com/watch?v=eCz0JdPqSaA"
  },
  {
    "Name": "Seberapa Pantas",
    "Artist": "Sheila on 7",
    "Link": "https://www.youtube.com/watch?v=OdDwIwoiZwU"
  },
  {
    "Name": "Bahagia",
    "Artist": "GAC",
    "Link": "https://www.youtube.com/watch?v=zDHOW9PdQYE"
  },
  {
    "Name": "Pelangi",
    "Artist": "Maliq & D'Essentials",
    "Link": "https://www.youtube.com/watch?v=NCRga9NO3No"
  },
  {
    "Name": "Dunia Tipu-Tipu",
    "Artist": "Yura Yunita",
    "Link": "https://www.youtube.com/watch?v=Jdj13fGMmmA"
  },
  {
    "Name": "Hari Bersamanya",
    "Artist": "Sheila on 7",
    "Link": "https://www.youtube.com/watch?v=32M1DDVwqeY"
  },
  {
    "Name": "Cinta dan Rahasia",
    "Artist": "Yura Yunita feat. Glenn Fredly",
    "Link": "https://www.youtube.com/watch?v=qhn0Hi97CoA"
  },
  {
    "Name": "Manusia Kuat",
    "Artist": "Tulus",
    "Link": "https://www.youtube.com/watch?v=f-fEeF12FH4"
  },
  {
    "Name": "Kasih Tak Sampai",
    "Artist": "Padi",
    "Link": "https://www.youtube.com/watch?v=v9SvqaLIGmU"
  },
  {
    "Name": "Andai Aku Bisa",
    "Artist": "Chrisye",
    "Link": "https://www.youtube.com/watch?v=GL8idVuo2y4"
  },
  {
    "Name": "Menemukanmu",
    "Artist": "Seventeen",
    "Link": "https://www.youtube.com/watch?v=0J5JEfOjskQ"
  },
  {
    "Name": "Bintang Kehidupan",
    "Artist": "Nike Ardilla",
    "Link": "https://www.youtube.com/watch?v=dXI4_dgfHJQ"
  },
  {
    "Name": "Cinta Ini Membunuhku",
    "Artist": "D'Masiv",
    "Link": "https://www.youtube.com/watch?v=iz7hDDlW8yQ"
  },
  {
    "Name": "Cinta Sejati",
    "Artist": "Bunga Citra Lestari",
    "Link": "https://www.youtube.com/watch?v=Bgt9g1q-xj0"
  },
  {
    "Name": "Sempurna",
    "Artist": "Andra and The Backbone",
    "Link": "https://www.youtube.com/watch?v=jStNaVCW838"
  },
  {
    "Name": "Mungkin Nanti",
    "Artist": "Peterpan",
    "Link": "https://www.youtube.com/watch?v=SWcMwUySDvI"
  },
  {
    "Name": "Janji Suci",
    "Artist": "Yovie & Nuno",
    "Link": "https://www.youtube.com/watch?v=hQ-wYw4hP84"
  },
  {
    "Name": "Kangen",
    "Artist": "Dewa 19",
    "Link": "https://www.youtube.com/watch?v=sjjhLDPT5_g"
  },
  {
    "Name": "Kita Selamanya",
    "Artist": "Project Pop",
    "Link": "https://www.youtube.com/watch?v=8KQ93aW7YY4"
  },
  {
    "Name": "Terlalu Manis",
    "Artist": "Slank",
    "Link": "https://www.youtube.com/watch?v=9ie7jxgsasw"
  },
  {
    "Name": "Hanya Cinta Yang Bisa",
    "Artist": "Titi DJ",
    "Link": "https://www.youtube.com/watch?v=pJA_4PGu8Yg"
  },
  {
    "Name": "Kenangan Terindah",
    "Artist": "Samsons",
    "Link": "https://www.youtube.com/watch?v=-yG8j2MGOyY"
  }
]