[
  {
    "Name": "Usai",
    "Artist": "Tiara Andini",
    "Link": "https://www.youtube.com/watch?v=83ntBBDC8Xs"
  },
  {
    "Name": "Tak Akan Hilang",
    "Artist": "Budi Doremi",
    "Link": "https://www.youtube.com/watch?v=Xi-nRpfFgDQ"
  },
  {
    "Name": "Runtuh",
    "Artist": "Feby Putri & Fiersa Besari",
    "Link": "https://www.youtube.com/watch?v=YrtS8MESh0I"
  },
  {
    "Name": "Tertawan Hati",
    "Artist": "Awdella",
    "Link": "https://www.youtube.com/watch?v=Xs_CTmgUke8"
  },
  {
    "Name": "Rumah Singgah",
    "Artist": "Fabio Asher",
    "Link": "https://www.youtube.com/watch?v=TRQjoymt28I"
  },
  {
    "Name": "Sang Dewi",
    "Artist": "Lyodra & Andi Rianto",
    "Link": "https://www.youtube.com/watch?v=c_Tv_VukoB0"
  },
  {
    "Name": "Apa Mungkin",
    "Artist": "Bernadya",
    "Link": "https://www.youtube.com/watch?v=iUbTrLJa1Xk"
  },
  {
    "Name": "Ternyata Hanya Kamu",
    "Artist": "Brisia Jodie & Stevan Pasaribu",
    "Link": "https://www.youtube.com/watch?v=K3gNQ7WP3kk"
  },
  {
    "Name": "Berpisah Lebih Indah",
    "Artist": "Riassa Ramadhani",
    "Link": "https://www.youtube.com/watch?v=wvt8SjIo4_c"
  },
  {
    "Name": "Kisah Sempurna",
    "Artist": "Mahalini",
    "Link": "https://www.youtube.com/watch?v=MHDLTcsdYQA"
  },
  {
    "Name": "Tak Ingin Usai",
    "Artist": "Keisya Levronka",
    "Link": "https://www.youtube.com/watch?v=FB1YNEOspyA"
  },
  {
    "Name": "Pilihan Yang Terbaik",
    "Artist": "Ziva Magnolya",
    "Link": "https://www.youtube.com/watch?v=0g9b7Mgm3oo"
  },
  {
    "Name": "Hati-hati di Jalan",
    "Artist": "Tulus",
    "Link": "https://www.youtube.com/watch?v=F4z8MKU3vEk"
  },
  {
    "Name": "Sisa Rasa",
    "Artist": "Mahalini",
    "Link": "https://www.youtube.com/watch?v=ADwD_Yhu_E0"
  },
  {
    "Name": "Menjadi Dia",
    "Artist": "Tiara Andini",
    "Link": "https://www.youtube.com/watch?v=wvS_ruoonhg"
  },
  {
    "Name": "Andaikan Kau Datang",
    "Artist": "Andmesh",
    "Link": "https://www.youtube.com/watch?v=HHLwAYaFnv8"
  },
  {
    "Name": "Selamat (Selamat Tinggal)",
    "Artist": "Virgoun & Audy",
    "Link": "https://www.youtube.com/watch?v=nnZpgbJQVXw"
  },
  {
    "Name": "Belum Sampai Kehilangan",
    "Artist": "Stevan Pasaribu",
    "Link": "https://www.youtube.com/watch?v=0ru5Ox8f_vs"
  },
  {
    "Name": "Bertahan Terluka",
    "Artist": "Fabio Asher",
    "Link": "https://www.youtube.com/watch?v=aFjr5Y81rY0"
  },
  {
    "Name": "To the Bone",
    "Artist": "Pamungkas",
    "Link": "https://www.youtube.com/watch?v=oIYWenB637c"
  },
  {
    "Name": "Bertaut",
    "Artist": "Nadin Amizah",
    "Link": "https://www.youtube.com/watch?v=WLaTirtb86s"
  },
  {
    "Name": "Tutur Batin",
    "Artist": "Yura Yunita",
    "Link": "https://www.youtube.com/watch?v=BbsePATM2ww"
  }
]